dangee/__init__.py
dangee/core.py
dangee/dangee_analysis.py
dangee/util/__init__.py
Dangee-0.0.3.dist-info/LICENSE
Dangee-0.0.3.dist-info/METADATA
Dangee-0.0.3.dist-info/WHEEL
Dangee-0.0.3.dist-info/top_level.txt
Dangee-0.0.3.dist-info/RECORD
