Metadata-Version: 2.1
Name: Dangee
Version: 0.0.3
Summary: Dangee
Home-page: https://github.com/quark-engine/Dangee
Author: JunWei Song
Author-email: sungboss2004@gmail.com
License: UNKNOWN
Platform: UNKNOWN
Classifier: Programming Language :: Python :: 3
Classifier: License :: OSI Approved :: GNU General Public License v3 (GPLv3)
Classifier: Operating System :: OS Independent
Classifier: Topic :: Security
Requires-Python: >=3.8
Requires-Dist: quark-engine
